chope_data_haidilao/__init__.py
chope_data_haidilao/client.py
chope_data_haidilao/conf/config.yaml
chope_data_haidilao/conf/env/dev.yaml
chope_data_haidilao/conf/feature_store/conf.yaml
chope_data_haidilao/conf/logging.ini
chope_data_haidilao/entity_values/__init__.py
chope_data_haidilao/entity_values/base.py
chope_data_haidilao/entity_values/merchant.py
chope_data_haidilao/pattern/__init__.py
chope_data_haidilao/pattern/formatter.py
chope_data_haidilao/request/__init__.py
chope_data_haidilao/request/dataframe.py
chope_data_haidilao/request/requester.py
chope_data_haidilao/retrieval/__init__.py
chope_data_haidilao/retrieval/bigquery.py
chope_data_haidilao/utils.py
chope_data_haidilao-0.1.6.dist-info/WHEEL
chope_data_haidilao-0.1.6.dist-info/METADATA
chope_data_haidilao-0.1.6.dist-info/RECORD
