Metadata-Version: 2.1
Name: chope-data-haidilao
Version: 0.1.6
Summary: Featurestore wrapper
Author: Quy Dinh
Author-email: quy.d@chope.co
Requires-Python: >=3.8,<4.0
Classifier: Programming Language :: Python :: 3
Classifier: Programming Language :: Python :: 3.10
Classifier: Programming Language :: Python :: 3.8
Classifier: Programming Language :: Python :: 3.9
Requires-Dist: cloudpickle (==2.0.0)
Requires-Dist: google-cloud-aiplatform (>=1.6.0,<2.0.0)
Requires-Dist: google-cloud-bigquery
Requires-Dist: google-cloud-bigquery-storage (>=2.10.1,<3.0.0)
Requires-Dist: google-cloud-storage
Requires-Dist: hydra-core
Requires-Dist: pandas
Requires-Dist: pyarrow
Requires-Dist: python-dotenv
